setuptools_twine/__init__.py
setuptools_twine/commands.py
setuptools_twine-0.1.3.dist-info/LICENSE
setuptools_twine-0.1.3.dist-info/METADATA
setuptools_twine-0.1.3.dist-info/WHEEL
setuptools_twine-0.1.3.dist-info/entry_points.txt
setuptools_twine-0.1.3.dist-info/top_level.txt
setuptools_twine-0.1.3.dist-info/RECORD
