Metadata-Version: 2.1
Name: setuptools-twine
Version: 0.1.3
Summary: Adds twine_check and twine_upload commands to setuptools.
Home-page: https://github.com/cchurch/setuptools-twine
Author: Nine More Minutes, Inc.
Author-email: chris@ninemoreminutes.com
License: BSD
Project-URL: Documentation, https://github.com/cchurch/setuptools-twine/blob/master/README.rst
Project-URL: Source, https://github.com/cchurch/setuptools-twine
Project-URL: Tracker, https://github.com/cchurch/setuptools-twine/issues
Keywords: setuptools,twine
Platform: UNKNOWN
Classifier: Development Status :: 3 - Alpha
Classifier: Environment :: Console
Classifier: Framework :: Setuptools Plugin
Classifier: Intended Audience :: Developers
Classifier: License :: OSI Approved :: BSD License
Classifier: Operating System :: OS Independent
Classifier: Programming Language :: Python
Classifier: Programming Language :: Python :: 2.7
Classifier: Programming Language :: Python :: 3
Classifier: Programming Language :: Python :: 3.5
Classifier: Programming Language :: Python :: 3.6
Classifier: Programming Language :: Python :: 3.7
Classifier: Programming Language :: Python :: 3.8
Classifier: Programming Language :: Python :: 3.9
Classifier: Topic :: Software Development :: Build Tools
Requires-Dist: setuptools
Requires-Dist: twine
